travel_recommender/__init__.py
travel_recommender/recommender.py
travel_recommender/utils.py
travel_recommender-0.1.0.dist-info/METADATA
travel_recommender-0.1.0.dist-info/WHEEL
travel_recommender-0.1.0.dist-info/top_level.txt
travel_recommender-0.1.0.dist-info/RECORD
